nengo_spa/__init__.py
nengo_spa/action_selection.py
nengo_spa/conftest.py
nengo_spa/connectors.py
nengo_spa/examine.py
nengo_spa/exceptions.py
nengo_spa/math.py
nengo_spa/network.py
nengo_spa/operators.py
nengo_spa/semantic_pointer.py
nengo_spa/testing.py
nengo_spa/typechecks.py
nengo_spa/types.py
nengo_spa/vector_generation.py
nengo_spa/version.py
nengo_spa/vocabulary.py
nengo_spa/algebras/__init__.py
nengo_spa/algebras/base.py
nengo_spa/algebras/hrr_algebra.py
nengo_spa/algebras/tvtb_algebra.py
nengo_spa/algebras/vtb_algebra.py
nengo_spa/algebras/tests/test_algebras.py
nengo_spa/algebras/tests/test_hrr_algebra.py
nengo_spa/algebras/tests/test_tvtb_algebra.py
nengo_spa/algebras/tests/test_vtb_algebra.py
nengo_spa/ast/__init__.py
nengo_spa/ast/base.py
nengo_spa/ast/dynamic.py
nengo_spa/ast/expr_tree.py
nengo_spa/ast/symbolic.py
nengo_spa/ast/tests/__init__.py
nengo_spa/ast/tests/test_dynamic.py
nengo_spa/ast/tests/test_expr_tree.py
nengo_spa/ast/tests/test_symbolic.py
nengo_spa/modules/__init__.py
nengo_spa/modules/associative_memory.py
nengo_spa/modules/basalganglia.py
nengo_spa/modules/bind.py
nengo_spa/modules/compare.py
nengo_spa/modules/product.py
nengo_spa/modules/scalar.py
nengo_spa/modules/state.py
nengo_spa/modules/superposition.py
nengo_spa/modules/thalamus.py
nengo_spa/modules/transcode.py
nengo_spa/modules/tests/__init__.py
nengo_spa/modules/tests/test_associative_memory.py
nengo_spa/modules/tests/test_basalganglia.py
nengo_spa/modules/tests/test_bind.py
nengo_spa/modules/tests/test_compare.py
nengo_spa/modules/tests/test_cortical.py
nengo_spa/modules/tests/test_state.py
nengo_spa/modules/tests/test_superposition.py
nengo_spa/modules/tests/test_thalamus.py
nengo_spa/modules/tests/test_transcode.py
nengo_spa/networks/__init__.py
nengo_spa/networks/circularconvolution.py
nengo_spa/networks/identity_ensemble_array.py
nengo_spa/networks/matrix_multiplication.py
nengo_spa/networks/selection.py
nengo_spa/networks/tvtb.py
nengo_spa/networks/vtb.py
nengo_spa-2.0.0.dist-info/LICENSE.rst
nengo_spa-2.0.0.dist-info/METADATA
nengo_spa-2.0.0.dist-info/WHEEL
nengo_spa-2.0.0.dist-info/top_level.txt
nengo_spa-2.0.0.dist-info/RECORD
