Metadata-Version: 2.1
Name: nengo-spa
Version: 2.0.0
Summary: An implementation of the Semantic Pointer Architecture for Nengo
Home-page: https://www.nengo.ai/nengo-spa
Author: Applied Brain Research
Author-email: info@appliedbrainresearch.com
License: GNU General Public License, version 2
Classifier: Development Status :: 5 - Production/Stable
Classifier: Framework :: Nengo
Classifier: Intended Audience :: Science/Research
Classifier: License :: OSI Approved :: GNU General Public License v2 (GPLv2)
Classifier: Operating System :: OS Independent
Classifier: Programming Language :: Python :: 3 :: Only
Classifier: Programming Language :: Python :: 3.6
Classifier: Programming Language :: Python :: 3.7
Classifier: Programming Language :: Python :: 3.8
Classifier: Programming Language :: Python :: 3.9
Classifier: Topic :: Scientific/Engineering :: Artificial Intelligence
Requires-Python: >=3.8
License-File: LICENSE.rst
Requires-Dist: nengo (>=2.7)
Requires-Dist: numpy (>=1.8)
Provides-Extra: all
Requires-Dist: jupyter ; extra == 'all'
Requires-Dist: matplotlib (>=2.0) ; extra == 'all'
Requires-Dist: nbsphinx (>=0.8.11) ; extra == 'all'
Requires-Dist: nengo-sphinx-theme ; extra == 'all'
Requires-Dist: numpydoc (>=1.4.0) ; extra == 'all'
Requires-Dist: scipy (>=1.4.1) ; extra == 'all'
Requires-Dist: scikit-learn ; extra == 'all'
Requires-Dist: jupyter (>=1.0.0) ; extra == 'all'
Requires-Dist: nbformat (>=5.0.7) ; extra == 'all'
Requires-Dist: pytest (>=3.6) ; extra == 'all'
Requires-Dist: pytest-plt ; extra == 'all'
Requires-Dist: pytest-rng ; extra == 'all'
Provides-Extra: docs
Requires-Dist: jupyter ; extra == 'docs'
Requires-Dist: matplotlib (>=2.0) ; extra == 'docs'
Requires-Dist: nbsphinx (>=0.8.11) ; extra == 'docs'
Requires-Dist: nengo-sphinx-theme ; extra == 'docs'
Requires-Dist: numpydoc (>=1.4.0) ; extra == 'docs'
Provides-Extra: optional
Requires-Dist: scipy (>=1.4.1) ; extra == 'optional'
Requires-Dist: scikit-learn ; extra == 'optional'
Provides-Extra: tests
Requires-Dist: jupyter (>=1.0.0) ; extra == 'tests'
Requires-Dist: matplotlib (>=2.0) ; extra == 'tests'
Requires-Dist: nbformat (>=5.0.7) ; extra == 'tests'
Requires-Dist: pytest (>=3.6) ; extra == 'tests'
Requires-Dist: pytest-plt ; extra == 'tests'
Requires-Dist: pytest-rng ; extra == 'tests'
